data_team_py_slack_notifier/__init__.py
data_team_py_slack_notifier/data_team_py_slack_notifier.py
chip_data_team_py_slack_notifier-1.0.3.dist-info/LICENSE
chip_data_team_py_slack_notifier-1.0.3.dist-info/METADATA
chip_data_team_py_slack_notifier-1.0.3.dist-info/WHEEL
chip_data_team_py_slack_notifier-1.0.3.dist-info/top_level.txt
chip_data_team_py_slack_notifier-1.0.3.dist-info/RECORD
